sqlalchemy_rdsiam/__init__.py
sqlalchemy_rdsiam/build.py
sqlalchemy_rdsiam/dbapi_asyncpg.py
sqlalchemy_rdsiam/dbapi_psycopg2.py
sqlalchemy_rdsiam/dialects.py
sqlalchemy_rdsiam/rds.py
sqlalchemy_rdsiam/sslrootcert.py
sqlalchemy_rdsiam/rds-ca-bundle/global-bundle.pem
sqlalchemy_rdsiam-1.0.3.dist-info/LICENSE
sqlalchemy_rdsiam-1.0.3.dist-info/METADATA
sqlalchemy_rdsiam-1.0.3.dist-info/WHEEL
sqlalchemy_rdsiam-1.0.3.dist-info/entry_points.txt
sqlalchemy_rdsiam-1.0.3.dist-info/top_level.txt
sqlalchemy_rdsiam-1.0.3.dist-info/RECORD
