Metadata-Version: 2.1
Name: sqlalchemy-rdsiam
Version: 1.0.3
Summary: SQLAlchemy dialects to connect to Amazon RDS instances with IAM authentication
Home-page: https://github.com/cisco-open/sqlalchemy-rdsiam
Classifier: Development Status :: 4 - Beta
Classifier: Environment :: Console
Classifier: Intended Audience :: Developers
Classifier: Operating System :: OS Independent
Classifier: Programming Language :: Python
Classifier: Programming Language :: Python :: 3
Classifier: Programming Language :: Python :: 3.6
Classifier: Programming Language :: Python :: 3.7
Classifier: Programming Language :: Python :: 3.8
Classifier: Programming Language :: Python :: 3.9
Classifier: Programming Language :: Python :: 3.10
Classifier: Programming Language :: Python :: 3.11
Requires-Python: >=3.6
License-File: LICENSE
Requires-Dist: SQLAlchemy >=1.3
Requires-Dist: boto3
